{
  "project": "safe-helpline-india",
  "country": "India",
  "lastUpdated": "2026-06-26",
  "disclaimer": "This dataset is for public safety awareness only. In an emergency, contact official emergency services directly.",
  "helplines": [
    {
      "id": "india-erss-112",
      "name": "Emergency Response Support System",
      "number": "112",
      "type": "emergency",
      "available": "24x7",
      "description": "Nationwide single emergency number for reporting and addressing emergencies across India.",
      "source": "https://www.mha.gov.in/en/commoncontent/emergency-response-support-system-erss"
    },
    {
      "id": "india-women-helpline-181",
      "name": "Women Helpline",
      "number": "181",
      "type": "women_safety",
      "available": "24x7",
      "description": "Emergency and non-emergency response for women through telephonic short-code 181.",
      "source": "https://www.myscheme.gov.in/schemes/whl-181"
    }
  ]
}
